salientsdk/.gitignore
salientsdk/__init__.py
salientsdk/__main__.py
salientsdk/cli.py
salientsdk/constants.py
salientsdk/data/.gitignore
salientsdk/data/cmeus.csv
salientsdk/data/ecmwf_ens_dates.csv
salientsdk/data/long-range_dates.csv
salientsdk/data/power_curves.csv
salientsdk/data/region.nc
salientsdk/data/seasonal_dates.csv
salientsdk/data/sub-seasonal_dates.csv
salientsdk/data/vic_soil_texture_lookup.csv
salientsdk/data/vic_veg_lookup.csv
salientsdk/data_timeseries_api.py
salientsdk/derived.py
salientsdk/downscale_api.py
salientsdk/event.py
salientsdk/examples/.gitignore
salientsdk/examples/cloudflare_access.ipynb
salientsdk/examples/conftest.py
salientsdk/examples/custom_quantity.ipynb
salientsdk/examples/downscale.ipynb
salientsdk/examples/enwex.ipynb
salientsdk/examples/hindcast_summary.ipynb
salientsdk/examples/ski.ipynb
salientsdk/examples/solar.ipynb
salientsdk/examples/trend.ipynb
salientsdk/examples/validate.ipynb
salientsdk/examples/validate_downscale.ipynb
salientsdk/examples/validate_gem.ipynb
salientsdk/examples/wind.ipynb
salientsdk/forecast_timeseries_api.py
salientsdk/forecast_zarr.py
salientsdk/gem_utils.py
salientsdk/geo_api.py
salientsdk/hindcast_summary_api.py
salientsdk/hydro.py
salientsdk/location.py
salientsdk/login_api.py
salientsdk/met_api.py
salientsdk/skill.py
salientsdk/solar.py
salientsdk/upload_file_api.py
salientsdk/vulture_whitelist.py
salientsdk/wind.py
salientsdk-0.3.46.dist-info/METADATA
salientsdk-0.3.46.dist-info/WHEEL
salientsdk-0.3.46.dist-info/entry_points.txt
salientsdk-0.3.46.dist-info/RECORD
