Metadata-Version: 2.3
Name: salientsdk
Version: 0.3.46
Summary: Salient Predictions Software Development Kit
License: LicenseRef-Custom
Keywords: weather,climate,forecasting,sdk,salient,s2s
Author: Salient Predictions
Author-email: help@salientpredictions.com
Requires-Python: >=3.10,<4.0
Classifier: License :: Other/Proprietary License
Classifier: Programming Language :: Python :: 3
Classifier: Programming Language :: Python :: 3.10
Classifier: Programming Language :: Python :: 3.11
Classifier: Programming Language :: Python :: 3.12
Classifier: Programming Language :: Python :: 3.13
Requires-Dist: backoff (>=2.2.1,<3.0.0)
Requires-Dist: bottleneck (>=1.3.8)
Requires-Dist: cartopy (>=0.18.0)
Requires-Dist: dask (>=2024.4.2)
Requires-Dist: geopandas (>=0.14.4)
Requires-Dist: google (>=3.0.0,<4.0.0)
Requires-Dist: google-cloud-secret-manager (>=2.19.0,<3.0.0)
Requires-Dist: h5netcdf (>=1.3.0,<2.0.0)
Requires-Dist: jinja2 (>=3.1.6,<4.0.0)
Requires-Dist: metpy (>=1.7.1,<2.0.0)
Requires-Dist: netcdf4 (>=1.6.5,<2.0.0)
Requires-Dist: numpy (>=1.24.4,<3.0.0)
Requires-Dist: pandas (>=2.2.0,<3.0.0)
Requires-Dist: pcodec (>=0.3.4,<0.4.0)
Requires-Dist: pint-xarray (>=0.4,<0.5)
Requires-Dist: pvlib (>=0.10.5,<0.11.0)
Requires-Dist: pyarrow (>=14.0.0)
Requires-Dist: ratelimit (>=2.2.1,<3.0.0)
Requires-Dist: requests (>=2.31.0,<3.0.0)
Requires-Dist: s3fs (>=2025.2.0,<2026.0.0)
Requires-Dist: scikit-learn (>=1.1.3)
Requires-Dist: scipy (>=1.11.4)
Requires-Dist: toml (>=0.10.2,<0.11.0)
Requires-Dist: xarray (>=2024.3.0)
Requires-Dist: zarr (==2.17.1)
Project-URL: Documentation, https://salient-predictions.github.io/salientsdk
Project-URL: Homepage, https://salientpredictions.com
Project-URL: License, https://sdk.salientpredictions.com/LICENSE/
Project-URL: Repository, https://github.com/Salient-Predictions/salientsdk
